django_soft_atomic.py
django_soft_atomic-1.1.0.dist-info/METADATA
django_soft_atomic-1.1.0.dist-info/WHEEL
django_soft_atomic-1.1.0.dist-info/licenses/LICENSE
django_soft_atomic-1.1.0.dist-info/RECORD
