Metadata-Version: 2.1
Name: django_soft_atomic
Version: 1.1.0
Summary: A more forgiving variation of django's transaction handling, allowing you to pass some exceptions through atomic block without rollback.
Project-URL: Homepage, https://github.com/maniek2332/django_soft_atomic
Project-URL: Bug Tracker, https://github.com/maniek2332/django_soft_atomic/issues
Author-email: Mariusz Okulanis <mariusz.okulanis@gmail.com>
License-File: LICENSE
Classifier: Development Status :: 5 - Production/Stable
Classifier: Framework :: Django
Classifier: Framework :: Django :: 3.2
Classifier: Framework :: Django :: 4
Classifier: Framework :: Django :: 4.0
Classifier: Framework :: Django :: 4.1
Classifier: License :: OSI Approved :: MIT License
Classifier: Operating System :: OS Independent
Classifier: Programming Language :: Python :: 3
Classifier: Topic :: Database
Classifier: Topic :: Software Development
Classifier: Topic :: Utilities
Requires-Python: >=3.6
Requires-Dist: django>=3.2
